prime-gen/__init__.py
prime_gen/__init__.py
prime_gen-1.0.2.dist-info/LICENSE
prime_gen-1.0.2.dist-info/METADATA
prime_gen-1.0.2.dist-info/WHEEL
prime_gen-1.0.2.dist-info/top_level.txt
prime_gen-1.0.2.dist-info/RECORD
